{
  "modifier_class": "",
  "button_modifier_class": "",
  "toggle_text": "Menu",
  "lv1": [
    {
      "href": "/",
      "text": "Home"
    },
    {
      "href": "#",
      "text": "Useful Websites",
      "lv2": [
        {
          "href": "https://www.stanford.edu",
          "text": "Stanford",
          "target": "_blank"
        },
        {
          "href": "https://uit.stanford.edu/sws",
          "text": "Stanford Web Services",
          "target": "_blank"
        },
        {
          "href": "https://ucomm.stanford.edu/",
          "text": "University Communications"
        },
        {
          "href": "/section-components.htm",
          "text": "Decanter components",
          "current": true
        }
      ]
    },
    {
      "href": "#",
      "text": "Tools & Documentations",
      "lv2": [
        {
          "href": "https://www.figma.com/",
          "text": "Figma"
        },
        {
          "href": "https://twig.symfony.com/doc/2.x/",
          "text": "Twig"
        }
      ]
    },
    {
      "href": "https://stackoverflow.com/",
      "text": "Developer Help",
      "current": true
    },
    {
      "href": "#",
      "text": "Other Useful Resources",
      "lv2": [
        {
          "href": "https://www.stanford.edu/faculty-staff-gateway/",
          "text": "Faculty & Staff Gateway"
        },
        {
          "href": "https://www.stanford.edu/student-gateway/",
          "text": "Student Gateway"
        },
        {
          "href": "https://uit.stanford.edu/launchpad",
          "text": "What Happens If My Second Level Link Text is Really Really Long"
        },
        {
          "href": "https://uit.stanford.edu/launchpad",
          "text": "Tools Launchpad"
        }
      ]
    }
  ]
}
